{
  "apiVersion": "dashboard.grafana.app/v2",
  "kind": "Dashboard",
  "metadata": {
    "name": "messenger-technical-kpi",
    "namespace": "default",
    "uid": "6ecb92cc-2b3a-4a55-8bdc-289ed582b3ab",
    "resourceVersion": "1777217004509018",
    "generation": 7,
    "creationTimestamp": "2026-04-26T14:26:36Z",
    "labels": {
      "grafana.app/deprecatedInternalID": "3774174348193792"
    },
    "annotations": {
      "grafana.app/createdBy": "user:cfk9femu897uoc",
      "grafana.app/folder": "",
      "grafana.app/message": "final",
      "grafana.app/saved-from-ui": "Grafana v13.0.1 (a100054f)",
      "grafana.app/updatedBy": "user:cfk9femu897uoc",
      "grafana.app/updatedTimestamp": "2026-04-26T15:23:24Z"
    }
  },
  "spec": {
    "annotations": [
      {
        "kind": "AnnotationQuery",
        "spec": {
          "query": {
            "kind": "DataQuery",
            "group": "grafana",
            "version": "v0",
            "datasource": {
              "name": "-- Grafana --"
            },
            "spec": {}
          },
          "enable": true,
          "hide": true,
          "iconColor": "rgba(0, 211, 255, 1)",
          "name": "Annotations & Alerts",
          "builtIn": true
        }
      }
    ],
    "cursorSync": "Off",
    "editable": true,
    "elements": {
      "panel-1": {
        "kind": "Panel",
        "spec": {
          "id": 1,
          "title": "Memory Usage %",
          "description": "",
          "links": [],
          "data": {
            "kind": "QueryGroup",
            "spec": {
              "queries": [
                {
                  "kind": "PanelQuery",
                  "spec": {
                    "query": {
                      "kind": "DataQuery",
                      "group": "grafana-clickhouse-datasource",
                      "version": "v0",
                      "datasource": {
                        "name": "clickhouse"
                      },
                      "spec": {
                        "editorType": "sql",
                        "format": 1,
                        "meta": {},
                        "pluginVersion": "4.15.0",
                        "queryType": "table",
                        "rawSql": "SELECT argMax(memory_usage_percent, timestamp) AS value\nFROM grafana_kpi_metrics\nWHERE $__timeFilter(timestamp)"
                      }
                    },
                    "refId": "A",
                    "hidden": false
                  }
                }
              ],
              "transformations": [],
              "queryOptions": {}
            }
          },
          "vizConfig": {
            "kind": "VizConfig",
            "group": "stat",
            "version": "13.0.1",
            "spec": {
              "options": {
                "colorMode": "value",
                "graphMode": "area",
                "justifyMode": "auto",
                "orientation": "auto",
                "percentChangeColorMode": "standard",
                "reduceOptions": {
                  "calcs": [
                    "lastNotNull"
                  ],
                  "fields": "",
                  "values": false
                },
                "showPercentChange": false,
                "textMode": "auto",
                "wideLayout": true
              },
              "fieldConfig": {
                "defaults": {
                  "unit": "percent",
                  "min": 0,
                  "max": 100,
                  "thresholds": {
                    "mode": "absolute",
                    "steps": [
                      {
                        "value": 0,
                        "color": "green"
                      },
                      {
                        "value": 70,
                        "color": "orange"
                      },
                      {
                        "value": 85,
                        "color": "red"
                      }
                    ]
                  },
                  "color": {
                    "mode": "thresholds"
                  }
                },
                "overrides": []
              }
            }
          }
        }
      },
      "panel-10": {
        "kind": "Panel",
        "spec": {
          "id": 10,
          "title": "HTTP Request Duration (ms)",
          "description": "",
          "links": [],
          "data": {
            "kind": "QueryGroup",
            "spec": {
              "queries": [
                {
                  "kind": "PanelQuery",
                  "spec": {
                    "query": {
                      "kind": "DataQuery",
                      "group": "grafana-clickhouse-datasource",
                      "version": "v0",
                      "datasource": {
                        "name": "clickhouse"
                      },
                      "spec": {
                        "editorType": "sql",
                        "format": 0,
                        "meta": {},
                        "pluginVersion": "4.15.0",
                        "queryType": "timeseries",
                        "rawSql": "SELECT timestamp AS time, http_request_duration_ms AS \"HTTP Duration (ms)\" FROM grafana_kpi_metrics WHERE $__timeFilter(timestamp) ORDER BY timestamp"
                      }
                    },
                    "refId": "A",
                    "hidden": false
                  }
                }
              ],
              "transformations": [],
              "queryOptions": {}
            }
          },
          "vizConfig": {
            "kind": "VizConfig",
            "group": "timeseries",
            "version": "13.0.1",
            "spec": {
              "options": {
                "annotations": {
                  "clustering": -1,
                  "multiLane": false
                },
                "legend": {
                  "calcs": [],
                  "displayMode": "list",
                  "placement": "bottom",
                  "showLegend": true
                },
                "tooltip": {
                  "hideZeros": false,
                  "mode": "single",
                  "sort": "none"
                }
              },
              "fieldConfig": {
                "defaults": {
                  "thresholds": {
                    "mode": "absolute",
                    "steps": [
                      {
                        "value": 0,
                        "color": "green"
                      },
                      {
                        "value": 80,
                        "color": "red"
                      }
                    ]
                  },
                  "color": {
                    "mode": "palette-classic"
                  },
                  "custom": {
                    "axisBorderShow": false,
                    "axisCenteredZero": false,
                    "axisColorMode": "text",
                    "axisLabel": "",
                    "axisPlacement": "auto",
                    "barAlignment": 0,
                    "barWidthFactor": 0.6,
                    "drawStyle": "line",
                    "fillOpacity": 0,
                    "gradientMode": "none",
                    "hideFrom": {
                      "legend": false,
                      "tooltip": false,
                      "viz": false
                    },
                    "insertNulls": false,
                    "lineInterpolation": "linear",
                    "lineWidth": 1,
                    "pointSize": 5,
                    "scaleDistribution": {
                      "type": "linear"
                    },
                    "showPoints": "auto",
                    "showValues": false,
                    "spanNulls": false,
                    "stacking": {
                      "group": "A",
                      "mode": "none"
                    },
                    "thresholdsStyle": {
                      "mode": "off"
                    }
                  }
                },
                "overrides": []
              }
            }
          }
        }
      },
      "panel-2": {
        "kind": "Panel",
        "spec": {
          "id": 2,
          "title": "CPU %",
          "description": "",
          "links": [],
          "data": {
            "kind": "QueryGroup",
            "spec": {
              "queries": [
                {
                  "kind": "PanelQuery",
                  "spec": {
                    "query": {
                      "kind": "DataQuery",
                      "group": "grafana-clickhouse-datasource",
                      "version": "v0",
                      "datasource": {
                        "name": "clickhouse"
                      },
                      "spec": {
                        "editorType": "sql",
                        "format": 1,
                        "meta": {},
                        "pluginVersion": "4.15.0",
                        "queryType": "table",
                        "rawSql": "SELECT argMax(cpu_utilization_percent, timestamp) AS value \nFROM grafana_kpi_metrics \nWHERE $__timeFilter(timestamp)"
                      }
                    },
                    "refId": "A",
                    "hidden": false
                  }
                }
              ],
              "transformations": [],
              "queryOptions": {}
            }
          },
          "vizConfig": {
            "kind": "VizConfig",
            "group": "stat",
            "version": "13.0.1",
            "spec": {
              "options": {
                "colorMode": "value",
                "graphMode": "area",
                "justifyMode": "auto",
                "orientation": "auto",
                "percentChangeColorMode": "standard",
                "reduceOptions": {
                  "calcs": [
                    "lastNotNull"
                  ],
                  "fields": "",
                  "values": false
                },
                "showPercentChange": false,
                "textMode": "auto",
                "wideLayout": true
              },
              "fieldConfig": {
                "defaults": {
                  "unit": "percent",
                  "min": 0,
                  "max": 100,
                  "thresholds": {
                    "mode": "absolute",
                    "steps": [
                      {
                        "value": 0,
                        "color": "green"
                      },
                      {
                        "value": 60,
                        "color": "orange"
                      },
                      {
                        "value": 80,
                        "color": "red"
                      }
                    ]
                  },
                  "color": {
                    "mode": "thresholds"
                  }
                },
                "overrides": []
              }
            }
          }
        }
      },
      "panel-3": {
        "kind": "Panel",
        "spec": {
          "id": 3,
          "title": "Threads",
          "description": "",
          "links": [],
          "data": {
            "kind": "QueryGroup",
            "spec": {
              "queries": [
                {
                  "kind": "PanelQuery",
                  "spec": {
                    "query": {
                      "kind": "DataQuery",
                      "group": "grafana-clickhouse-datasource",
                      "version": "v0",
                      "datasource": {
                        "name": "clickhouse"
                      },
                      "spec": {
                        "editorType": "sql",
                        "format": 1,
                        "meta": {},
                        "pluginVersion": "4.15.0",
                        "queryType": "table",
                        "rawSql": "SELECT argMax(thread_count, timestamp) AS value\nFROM grafana_kpi_metrics\nWHERE $__timeFilter(timestamp)"
                      }
                    },
                    "refId": "A",
                    "hidden": false
                  }
                }
              ],
              "transformations": [],
              "queryOptions": {}
            }
          },
          "vizConfig": {
            "kind": "VizConfig",
            "group": "stat",
            "version": "13.0.1",
            "spec": {
              "options": {
                "colorMode": "value",
                "graphMode": "area",
                "justifyMode": "auto",
                "orientation": "auto",
                "percentChangeColorMode": "standard",
                "reduceOptions": {
                  "calcs": [
                    "lastNotNull"
                  ],
                  "fields": "",
                  "values": false
                },
                "showPercentChange": false,
                "textMode": "auto",
                "wideLayout": true
              },
              "fieldConfig": {
                "defaults": {
                  "thresholds": {
                    "mode": "absolute",
                    "steps": [
                      {
                        "value": 0,
                        "color": "green"
                      },
                      {
                        "value": 80,
                        "color": "red"
                      }
                    ]
                  }
                },
                "overrides": []
              }
            }
          }
        }
      },
      "panel-4": {
        "kind": "Panel",
        "spec": {
          "id": 4,
          "title": "GC Duration (ms)",
          "description": "",
          "links": [],
          "data": {
            "kind": "QueryGroup",
            "spec": {
              "queries": [
                {
                  "kind": "PanelQuery",
                  "spec": {
                    "query": {
                      "kind": "DataQuery",
                      "group": "grafana-clickhouse-datasource",
                      "version": "v0",
                      "datasource": {
                        "name": "clickhouse"
                      },
                      "spec": {
                        "editorType": "sql",
                        "format": 1,
                        "meta": {},
                        "pluginVersion": "4.15.0",
                        "queryType": "table",
                        "rawSql": "SELECT argMax(gc_duration_ms, timestamp) AS value\nFROM grafana_kpi_metrics\nWHERE $__timeFilter(timestamp)"
                      }
                    },
                    "refId": "A",
                    "hidden": false
                  }
                }
              ],
              "transformations": [],
              "queryOptions": {}
            }
          },
          "vizConfig": {
            "kind": "VizConfig",
            "group": "stat",
            "version": "13.0.1",
            "spec": {
              "options": {
                "colorMode": "value",
                "graphMode": "area",
                "justifyMode": "auto",
                "orientation": "auto",
                "percentChangeColorMode": "standard",
                "reduceOptions": {
                  "calcs": [
                    "lastNotNull"
                  ],
                  "fields": "",
                  "values": false
                },
                "showPercentChange": false,
                "textMode": "auto",
                "wideLayout": true
              },
              "fieldConfig": {
                "defaults": {
                  "unit": "ms",
                  "thresholds": {
                    "mode": "absolute",
                    "steps": [
                      {
                        "value": 0,
                        "color": "green"
                      },
                      {
                        "value": 80,
                        "color": "red"
                      }
                    ]
                  }
                },
                "overrides": []
              }
            }
          }
        }
      },
      "panel-5": {
        "kind": "Panel",
        "spec": {
          "id": 5,
          "title": "Memory Usage Over Time",
          "description": "",
          "links": [],
          "data": {
            "kind": "QueryGroup",
            "spec": {
              "queries": [
                {
                  "kind": "PanelQuery",
                  "spec": {
                    "query": {
                      "kind": "DataQuery",
                      "group": "grafana-clickhouse-datasource",
                      "version": "v0",
                      "datasource": {
                        "name": "clickhouse"
                      },
                      "spec": {
                        "editorType": "sql",
                        "format": 1,
                        "meta": {},
                        "pluginVersion": "4.15.0",
                        "queryType": "table",
                        "rawSql": "SELECT timestamp AS time, memory_usage_percent AS \"Usage %\", memory_committed_percent AS \"Committed %\" FROM grafana_kpi_metrics WHERE $__timeFilter(timestamp) ORDER BY timestamp"
                      }
                    },
                    "refId": "A",
                    "hidden": false
                  }
                }
              ],
              "transformations": [],
              "queryOptions": {}
            }
          },
          "vizConfig": {
            "kind": "VizConfig",
            "group": "timeseries",
            "version": "13.0.1",
            "spec": {
              "options": {
                "annotations": {
                  "clustering": -1,
                  "multiLane": false
                },
                "legend": {
                  "calcs": [],
                  "displayMode": "list",
                  "placement": "bottom",
                  "showLegend": true
                },
                "tooltip": {
                  "hideZeros": false,
                  "mode": "single",
                  "sort": "none"
                }
              },
              "fieldConfig": {
                "defaults": {
                  "thresholds": {
                    "mode": "absolute",
                    "steps": [
                      {
                        "value": 0,
                        "color": "green"
                      },
                      {
                        "value": 80,
                        "color": "red"
                      }
                    ]
                  },
                  "color": {
                    "mode": "palette-classic"
                  },
                  "custom": {
                    "axisBorderShow": false,
                    "axisCenteredZero": false,
                    "axisColorMode": "text",
                    "axisLabel": "",
                    "axisPlacement": "auto",
                    "barAlignment": 0,
                    "barWidthFactor": 0.6,
                    "drawStyle": "line",
                    "fillOpacity": 0,
                    "gradientMode": "none",
                    "hideFrom": {
                      "legend": false,
                      "tooltip": false,
                      "viz": false
                    },
                    "insertNulls": false,
                    "lineInterpolation": "linear",
                    "lineWidth": 1,
                    "pointSize": 5,
                    "scaleDistribution": {
                      "type": "linear"
                    },
                    "showPoints": "auto",
                    "showValues": false,
                    "spanNulls": false,
                    "stacking": {
                      "group": "A",
                      "mode": "none"
                    },
                    "thresholdsStyle": {
                      "mode": "off"
                    }
                  }
                },
                "overrides": []
              }
            }
          }
        }
      },
      "panel-6": {
        "kind": "Panel",
        "spec": {
          "id": 6,
          "title": "CPU & Threads",
          "description": "",
          "links": [],
          "data": {
            "kind": "QueryGroup",
            "spec": {
              "queries": [
                {
                  "kind": "PanelQuery",
                  "spec": {
                    "query": {
                      "kind": "DataQuery",
                      "group": "grafana-clickhouse-datasource",
                      "version": "v0",
                      "datasource": {
                        "name": "clickhouse"
                      },
                      "spec": {
                        "editorType": "sql",
                        "format": 0,
                        "meta": {},
                        "pluginVersion": "4.15.0",
                        "queryType": "timeseries",
                        "rawSql": "SELECT timestamp AS time, cpu_utilization_percent AS \"CPU %\", thread_count AS \"Threads\" FROM grafana_kpi_metrics WHERE $__timeFilter(timestamp) ORDER BY timestamp"
                      }
                    },
                    "refId": "A",
                    "hidden": false
                  }
                }
              ],
              "transformations": [],
              "queryOptions": {}
            }
          },
          "vizConfig": {
            "kind": "VizConfig",
            "group": "timeseries",
            "version": "13.0.1",
            "spec": {
              "options": {
                "annotations": {
                  "clustering": -1,
                  "multiLane": false
                },
                "legend": {
                  "calcs": [],
                  "displayMode": "list",
                  "placement": "bottom",
                  "showLegend": true
                },
                "tooltip": {
                  "hideZeros": false,
                  "mode": "single",
                  "sort": "none"
                }
              },
              "fieldConfig": {
                "defaults": {
                  "thresholds": {
                    "mode": "absolute",
                    "steps": [
                      {
                        "value": 0,
                        "color": "green"
                      },
                      {
                        "value": 80,
                        "color": "red"
                      }
                    ]
                  },
                  "color": {
                    "mode": "palette-classic"
                  },
                  "custom": {
                    "axisBorderShow": false,
                    "axisCenteredZero": false,
                    "axisColorMode": "text",
                    "axisLabel": "",
                    "axisPlacement": "auto",
                    "barAlignment": 0,
                    "barWidthFactor": 0.6,
                    "drawStyle": "line",
                    "fillOpacity": 0,
                    "gradientMode": "none",
                    "hideFrom": {
                      "legend": false,
                      "tooltip": false,
                      "viz": false
                    },
                    "insertNulls": false,
                    "lineInterpolation": "linear",
                    "lineWidth": 1,
                    "pointSize": 5,
                    "scaleDistribution": {
                      "type": "linear"
                    },
                    "showPoints": "auto",
                    "showValues": false,
                    "spanNulls": false,
                    "stacking": {
                      "group": "A",
                      "mode": "none"
                    },
                    "thresholdsStyle": {
                      "mode": "off"
                    }
                  }
                },
                "overrides": []
              }
            }
          }
        }
      },
      "panel-7": {
        "kind": "Panel",
        "spec": {
          "id": 7,
          "title": "GC Duration (ms)",
          "description": "",
          "links": [],
          "data": {
            "kind": "QueryGroup",
            "spec": {
              "queries": [
                {
                  "kind": "PanelQuery",
                  "spec": {
                    "query": {
                      "kind": "DataQuery",
                      "group": "grafana-clickhouse-datasource",
                      "version": "v0",
                      "datasource": {
                        "name": "clickhouse"
                      },
                      "spec": {
                        "editorType": "sql",
                        "format": 1,
                        "meta": {},
                        "pluginVersion": "4.15.0",
                        "queryType": "table",
                        "rawSql": "SELECT timestamp AS time, gc_duration_ms AS \"GC Duration (ms)\" FROM grafana_kpi_metrics WHERE $__timeFilter(timestamp) ORDER BY timestamp"
                      }
                    },
                    "refId": "A",
                    "hidden": false
                  }
                }
              ],
              "transformations": [],
              "queryOptions": {}
            }
          },
          "vizConfig": {
            "kind": "VizConfig",
            "group": "timeseries",
            "version": "13.0.1",
            "spec": {
              "options": {
                "annotations": {
                  "clustering": -1,
                  "multiLane": false
                },
                "legend": {
                  "calcs": [],
                  "displayMode": "list",
                  "placement": "bottom",
                  "showLegend": true
                },
                "tooltip": {
                  "hideZeros": false,
                  "mode": "single",
                  "sort": "none"
                }
              },
              "fieldConfig": {
                "defaults": {
                  "thresholds": {
                    "mode": "absolute",
                    "steps": [
                      {
                        "value": 0,
                        "color": "green"
                      },
                      {
                        "value": 80,
                        "color": "red"
                      }
                    ]
                  },
                  "color": {
                    "mode": "palette-classic"
                  },
                  "custom": {
                    "axisBorderShow": false,
                    "axisCenteredZero": false,
                    "axisColorMode": "text",
                    "axisLabel": "",
                    "axisPlacement": "auto",
                    "barAlignment": 0,
                    "barWidthFactor": 0.6,
                    "drawStyle": "line",
                    "fillOpacity": 0,
                    "gradientMode": "none",
                    "hideFrom": {
                      "legend": false,
                      "tooltip": false,
                      "viz": false
                    },
                    "insertNulls": false,
                    "lineInterpolation": "linear",
                    "lineWidth": 1,
                    "pointSize": 5,
                    "scaleDistribution": {
                      "type": "linear"
                    },
                    "showPoints": "auto",
                    "showValues": false,
                    "spanNulls": false,
                    "stacking": {
                      "group": "A",
                      "mode": "none"
                    },
                    "thresholdsStyle": {
                      "mode": "off"
                    }
                  }
                },
                "overrides": []
              }
            }
          }
        }
      },
      "panel-8": {
        "kind": "Panel",
        "spec": {
          "id": 8,
          "title": "Kafka Activity",
          "description": "",
          "links": [],
          "data": {
            "kind": "QueryGroup",
            "spec": {
              "queries": [
                {
                  "kind": "PanelQuery",
                  "spec": {
                    "query": {
                      "kind": "DataQuery",
                      "group": "grafana-clickhouse-datasource",
                      "version": "v0",
                      "datasource": {
                        "name": "clickhouse"
                      },
                      "spec": {
                        "editorType": "sql",
                        "format": 0,
                        "meta": {},
                        "pluginVersion": "4.15.0",
                        "queryType": "timeseries",
                        "rawSql": "SELECT timestamp AS time, kafka_messages_sent_per_minute AS \"Messages/min\", kafka_connection_count AS \"Connections\" FROM grafana_kpi_metrics WHERE $__timeFilter(timestamp) ORDER BY timestamp"
                      }
                    },
                    "refId": "A",
                    "hidden": false
                  }
                }
              ],
              "transformations": [],
              "queryOptions": {}
            }
          },
          "vizConfig": {
            "kind": "VizConfig",
            "group": "timeseries",
            "version": "13.0.1",
            "spec": {
              "options": {
                "annotations": {
                  "clustering": -1,
                  "multiLane": false
                },
                "legend": {
                  "calcs": [],
                  "displayMode": "list",
                  "placement": "bottom",
                  "showLegend": true
                },
                "tooltip": {
                  "hideZeros": false,
                  "mode": "single",
                  "sort": "none"
                }
              },
              "fieldConfig": {
                "defaults": {
                  "thresholds": {
                    "mode": "absolute",
                    "steps": [
                      {
                        "value": 0,
                        "color": "green"
                      },
                      {
                        "value": 80,
                        "color": "red"
                      }
                    ]
                  },
                  "color": {
                    "mode": "palette-classic"
                  },
                  "custom": {
                    "axisBorderShow": false,
                    "axisCenteredZero": false,
                    "axisColorMode": "text",
                    "axisLabel": "",
                    "axisPlacement": "auto",
                    "barAlignment": 0,
                    "barWidthFactor": 0.6,
                    "drawStyle": "line",
                    "fillOpacity": 0,
                    "gradientMode": "none",
                    "hideFrom": {
                      "legend": false,
                      "tooltip": false,
                      "viz": false
                    },
                    "insertNulls": false,
                    "lineInterpolation": "linear",
                    "lineWidth": 1,
                    "pointSize": 5,
                    "scaleDistribution": {
                      "type": "linear"
                    },
                    "showPoints": "auto",
                    "showValues": false,
                    "spanNulls": false,
                    "stacking": {
                      "group": "A",
                      "mode": "none"
                    },
                    "thresholdsStyle": {
                      "mode": "off"
                    }
                  }
                },
                "overrides": []
              }
            }
          }
        }
      },
      "panel-9": {
        "kind": "Panel",
        "spec": {
          "id": 9,
          "title": "Database Connections",
          "description": "",
          "links": [],
          "data": {
            "kind": "QueryGroup",
            "spec": {
              "queries": [
                {
                  "kind": "PanelQuery",
                  "spec": {
                    "query": {
                      "kind": "DataQuery",
                      "group": "grafana-clickhouse-datasource",
                      "version": "v0",
                      "datasource": {
                        "name": "clickhouse"
                      },
                      "spec": {
                        "editorType": "sql",
                        "format": 0,
                        "meta": {},
                        "pluginVersion": "4.15.0",
                        "queryType": "timeseries",
                        "rawSql": "SELECT timestamp AS time, db_connections_active AS \"Active\", db_connection_wait_time_ms AS \"Wait (ms)\", db_connection_use_time_ms AS \"Use (ms)\" FROM grafana_kpi_metrics WHERE $__timeFilter(timestamp) ORDER BY timestamp"
                      }
                    },
                    "refId": "A",
                    "hidden": false
                  }
                }
              ],
              "transformations": [],
              "queryOptions": {}
            }
          },
          "vizConfig": {
            "kind": "VizConfig",
            "group": "timeseries",
            "version": "13.0.1",
            "spec": {
              "options": {
                "annotations": {
                  "clustering": -1,
                  "multiLane": false
                },
                "legend": {
                  "calcs": [],
                  "displayMode": "list",
                  "placement": "bottom",
                  "showLegend": true
                },
                "tooltip": {
                  "hideZeros": false,
                  "mode": "single",
                  "sort": "none"
                }
              },
              "fieldConfig": {
                "defaults": {
                  "thresholds": {
                    "mode": "absolute",
                    "steps": [
                      {
                        "value": 0,
                        "color": "green"
                      },
                      {
                        "value": 80,
                        "color": "red"
                      }
                    ]
                  },
                  "color": {
                    "mode": "palette-classic"
                  },
                  "custom": {
                    "axisBorderShow": false,
                    "axisCenteredZero": false,
                    "axisColorMode": "text",
                    "axisLabel": "",
                    "axisPlacement": "auto",
                    "barAlignment": 0,
                    "barWidthFactor": 0.6,
                    "drawStyle": "line",
                    "fillOpacity": 0,
                    "gradientMode": "none",
                    "hideFrom": {
                      "legend": false,
                      "tooltip": false,
                      "viz": false
                    },
                    "insertNulls": false,
                    "lineInterpolation": "linear",
                    "lineWidth": 1,
                    "pointSize": 5,
                    "scaleDistribution": {
                      "type": "linear"
                    },
                    "showPoints": "auto",
                    "showValues": false,
                    "spanNulls": false,
                    "stacking": {
                      "group": "A",
                      "mode": "none"
                    },
                    "thresholdsStyle": {
                      "mode": "off"
                    }
                  }
                },
                "overrides": []
              }
            }
          }
        }
      }
    },
    "layout": {
      "kind": "GridLayout",
      "spec": {
        "items": [
          {
            "kind": "GridLayoutItem",
            "spec": {
              "x": 0,
              "y": 0,
              "width": 6,
              "height": 4,
              "element": {
                "kind": "ElementReference",
                "name": "panel-1"
              }
            }
          },
          {
            "kind": "GridLayoutItem",
            "spec": {
              "x": 6,
              "y": 0,
              "width": 6,
              "height": 4,
              "element": {
                "kind": "ElementReference",
                "name": "panel-2"
              }
            }
          },
          {
            "kind": "GridLayoutItem",
            "spec": {
              "x": 12,
              "y": 0,
              "width": 6,
              "height": 4,
              "element": {
                "kind": "ElementReference",
                "name": "panel-3"
              }
            }
          },
          {
            "kind": "GridLayoutItem",
            "spec": {
              "x": 18,
              "y": 0,
              "width": 6,
              "height": 4,
              "element": {
                "kind": "ElementReference",
                "name": "panel-4"
              }
            }
          },
          {
            "kind": "GridLayoutItem",
            "spec": {
              "x": 0,
              "y": 4,
              "width": 12,
              "height": 9,
              "element": {
                "kind": "ElementReference",
                "name": "panel-5"
              }
            }
          },
          {
            "kind": "GridLayoutItem",
            "spec": {
              "x": 12,
              "y": 4,
              "width": 12,
              "height": 9,
              "element": {
                "kind": "ElementReference",
                "name": "panel-6"
              }
            }
          },
          {
            "kind": "GridLayoutItem",
            "spec": {
              "x": 0,
              "y": 13,
              "width": 12,
              "height": 8,
              "element": {
                "kind": "ElementReference",
                "name": "panel-7"
              }
            }
          },
          {
            "kind": "GridLayoutItem",
            "spec": {
              "x": 12,
              "y": 13,
              "width": 12,
              "height": 8,
              "element": {
                "kind": "ElementReference",
                "name": "panel-8"
              }
            }
          },
          {
            "kind": "GridLayoutItem",
            "spec": {
              "x": 0,
              "y": 21,
              "width": 12,
              "height": 8,
              "element": {
                "kind": "ElementReference",
                "name": "panel-10"
              }
            }
          },
          {
            "kind": "GridLayoutItem",
            "spec": {
              "x": 12,
              "y": 21,
              "width": 12,
              "height": 8,
              "element": {
                "kind": "ElementReference",
                "name": "panel-9"
              }
            }
          }
        ]
      }
    },
    "links": [],
    "liveNow": false,
    "preload": false,
    "tags": [
      "messenger",
      "kpi",
      "technical",
      "jvm"
    ],
    "timeSettings": {
      "timezone": "browser",
      "from": "now-6h",
      "to": "now",
      "autoRefresh": "30s",
      "autoRefreshIntervals": [
        "5s",
        "10s",
        "30s",
        "1m",
        "5m",
        "15m"
      ],
      "hideTimepicker": false,
      "fiscalYearStartMonth": 0
    },
    "title": "Technical KPI",
    "variables": []
  }
}